kubeanno/__init__.py
kubeanno/_annotate.py
kubeanno/_info.py
kubeanno-0.0.2.dist-info/METADATA
kubeanno-0.0.2.dist-info/WHEEL
kubeanno-0.0.2.dist-info/top_level.txt
kubeanno-0.0.2.dist-info/RECORD
